{"0":[],"Area0":[{"Rate":5.0,"Id":"00001004","IdIndex":4},{"Rate":5.0,"Id":"00001005","IdIndex":5},{"Rate":5.0,"Id":"00001006","IdIndex":6}],"Area1":[{"Rate":2.0,"Id":"10011003","IdIndex":4},{"Rate":2.0,"Id":"10011017","IdIndex":17},{"Rate":2.0,"Id":"10011006","IdIndex":7},{"Rate":2.0,"Id":"10011027","IdIndex":26},{"Rate":2.0,"Id":"10011013","IdIndex":13},{"Rate":2.0,"Id":"10011010","IdIndex":11}],"Area2":[{"Rate":2.0,"Id":"10021006","IdIndex":36},{"Rate":2.0,"Id":"10021018","IdIndex":48},{"Rate":2.0,"Id":"10021019","IdIndex":49},{"Rate":2.0,"Id":"10021037","IdIndex":65},{"Rate":2.0,"Id":"10021008","IdIndex":38},{"Rate":2.0,"Id":"10021007","IdIndex":37},{"Rate":0.0,"Id":"10021012","IdIndex":42}],"Area15":[{"Rate":2.0,"Id":"10151041","IdIndex":581},{"Rate":2.0,"Id":"10151044","IdIndex":584},{"Rate":2.0,"Id":"10151047","IdIndex":587},{"Rate":2.0,"Id":"10151097","IdIndex":631},{"Rate":2.0,"Id":"10151099","IdIndex":632},{"Rate":2.0,"Id":"10151107","IdIndex":639},{"Rate":2.0,"Id":"10151139","IdIndex":667},{"Rate":2.0,"Id":"10151138","IdIndex":666},{"Rate":0.0,"Id":"10151048","IdIndex":588},{"Rate":0.0,"Id":"10151051","IdIndex":591}],"Area3":[{"Rate":2.0,"Id":"10031005","IdIndex":66},{"Rate":2.0,"Id":"10031008","IdIndex":69},{"Rate":2.0,"Id":"10031011","IdIndex":72},{"Rate":2.0,"Id":"10031012","IdIndex":73},{"Rate":2.0,"Id":"10031007","IdIndex":68},{"Rate":2.0,"Id":"10031024","IdIndex":83},{"Rate":2.0,"Id":"10031024","IdIndex":83}],"Area4":[{"Rate":2.0,"Id":"10041006","IdIndex":84},{"Rate":2.0,"Id":"10041009","IdIndex":87},{"Rate":2.0,"Id":"10041013","IdIndex":91},{"Rate":2.0,"Id":"10041023","IdIndex":100},{"Rate":2.0,"Id":"10041043","IdIndex":117},{"Rate":2.0,"Id":"10041007","IdIndex":85},{"Rate":2.0,"Id":"10041011","IdIndex":89},{"Rate":0.0,"Id":"10041015","IdIndex":93}],"Area5":[{"Rate":5.0,"Id":"10051008","IdIndex":140},{"Rate":5.0,"Id":"10051009","IdIndex":141},{"Rate":5.0,"Id":"10051010","IdIndex":142},{"Rate":0.0,"Id":"10051007","IdIndex":139}],"Area6":[{"Rate":3.0,"Id":"10061010","IdIndex":148},{"Rate":3.0,"Id":"10061011","IdIndex":149},{"Rate":3.0,"Id":"10061012","IdIndex":150},{"Rate":3.0,"Id":"10061016","IdIndex":154},{"Rate":0.0,"Id":"10061008","IdIndex":146},{"Rate":0.0,"Id":"10061009","IdIndex":147},{"Rate":0.0,"Id":"10061013","IdIndex":151},{"Rate":0.0,"Id":"10061014","IdIndex":152},{"Rate":0.0,"Id":"10061015","IdIndex":153}],"Area7":[{"Rate":2.0,"Id":"10071025","IdIndex":184},{"Rate":2.0,"Id":"10071026","IdIndex":185},{"Rate":2.0,"Id":"10071021","IdIndex":180},{"Rate":2.0,"Id":"10071045","IdIndex":201},{"Rate":2.0,"Id":"10071019","IdIndex":179},{"Rate":2.0,"Id":"10071040","IdIndex":197},{"Rate":2.0,"Id":"10071038","IdIndex":195},{"Rate":2.0,"Id":"10071037","IdIndex":194}],"Area8":[{"Rate":2.0,"Id":"10081012","IdIndex":200},{"Rate":2.0,"Id":"10081015","IdIndex":203},{"Rate":2.0,"Id":"10081017","IdIndex":205},{"Rate":2.0,"Id":"10081021","IdIndex":208},{"Rate":2.0,"Id":"10081026","IdIndex":212},{"Rate":2.0,"Id":"10081029","IdIndex":215},{"Rate":2.0,"Id":"10081022","IdIndex":209}],"Area9":[{"Rate":3.0,"Id":"10091184","IdIndex":70},{"Rate":3.0,"Id":"10091128","IdIndex":69},{"Rate":3.0,"Id":"10091037","IdIndex":65},{"Rate":3.0,"Id":"10091040","IdIndex":67},{"Rate":3.0,"Id":"10091125","IdIndex":68},{"Rate":3.0,"Id":"10091036","IdIndex":64},{"Rate":3.0,"Id":"10091039","IdIndex":66},{"Rate":0.0,"Id":"10093001","IdIndex":71}],"Area10":[{"Rate":2.0,"Id":"10101034","IdIndex":253},{"Rate":2.0,"Id":"10101017","IdIndex":238},{"Rate":2.0,"Id":"10101020","IdIndex":241},{"Rate":2.0,"Id":"10101054","IdIndex":271},{"Rate":2.0,"Id":"10101051","IdIndex":268},{"Rate":2.0,"Id":"10101032","IdIndex":252},{"Rate":2.0,"Id":"10101064","IdIndex":280},{"Rate":2.0,"Id":"10101027","IdIndex":247},{"Rate":0.0,"Id":"10101011","IdIndex":232}],"Area11":[{"Rate":2.0,"Id":"10111015","IdIndex":84},{"Rate":2.0,"Id":"10111018","IdIndex":85},{"Rate":2.0,"Id":"10111021","IdIndex":86},{"Rate":2.0,"Id":"10111028","IdIndex":87},{"Rate":2.0,"Id":"10111031","IdIndex":88},{"Rate":2.0,"Id":"10111055","IdIndex":90},{"Rate":2.0,"Id":"10111052","IdIndex":89},{"Rate":2.0,"Id":"10111072","IdIndex":91},{"Rate":0.0,"Id":"10111012","IdIndex":83},{"Rate":0.0,"Id":"10111100-boss0","IdIndex":92}],"Area13":[{"Rate":2.0,"Id":"10131016","IdIndex":346},{"Rate":2.0,"Id":"10131019","IdIndex":349},{"Rate":2.0,"Id":"10131053","IdIndex":379},{"Rate":2.0,"Id":"10131022","IdIndex":352},{"Rate":2.0,"Id":"10131073","IdIndex":397},{"Rate":2.0,"Id":"10131016","IdIndex":346},{"Rate":2.0,"Id":"10131063","IdIndex":388},{"Rate":2.0,"Id":"10131039","IdIndex":367},{"Rate":0.0,"Id":"10131001","IdIndex":342},{"Rate":0.0,"Id":"10131013","IdIndex":343}],"Area14":[{"Rate":2.0,"Id":"10141022","IdIndex":108},{"Rate":2.0,"Id":"10141025","IdIndex":109},{"Rate":2.0,"Id":"10141019","IdIndex":107},{"Rate":2.0,"Id":"10141043","IdIndex":111},{"Rate":2.0,"Id":"10141071","IdIndex":112},{"Rate":2.0,"Id":"10141029","IdIndex":110},{"Rate":2.0,"Id":"10141109","IdIndex":115},{"Rate":2.0,"Id":"10141081","IdIndex":113},{"Rate":0.0,"Id":"10141100-boss0","IdIndex":114}],"Area18":[{"Rate":4.0,"Id":"10181016","IdIndex":484},{"Rate":4.0,"Id":"10181019","IdIndex":487},{"Rate":4.0,"Id":"10181018","IdIndex":486},{"Rate":4.0,"Id":"10181021","IdIndex":489},{"Rate":0.0,"Id":"10181015","IdIndex":483}],"Area19":[{"Rate":2.0,"Id":"10191017","IdIndex":152},{"Rate":2.0,"Id":"10191020","IdIndex":153},{"Rate":2.0,"Id":"10191023","IdIndex":154},{"Rate":2.0,"Id":"10191042","IdIndex":157},{"Rate":2.0,"Id":"10191056","IdIndex":158},{"Rate":2.0,"Id":"10191039","IdIndex":156},{"Rate":2.0,"Id":"10191035","IdIndex":155},{"Rate":2.0,"Id":"10191042","IdIndex":157},{"Rate":0.0,"Id":"10191016","IdIndex":151},{"Rate":0.0,"Id":"10191100-boss0","IdIndex":159}],"Area20":[{"Rate":2.0,"Id":"10201018","IdIndex":564},{"Rate":2.0,"Id":"10201021","IdIndex":567},{"Rate":2.0,"Id":"10201030","IdIndex":575},{"Rate":2.0,"Id":"10201033","IdIndex":578},{"Rate":2.0,"Id":"10201020","IdIndex":566},{"Rate":2.0,"Id":"10201023","IdIndex":569},{"Rate":2.0,"Id":"10201043","IdIndex":587},{"Rate":0.0,"Id":"10201017","IdIndex":563}],"Area21":[{"Rate":2.0,"Id":"10211019","IdIndex":169},{"Rate":2.0,"Id":"10211022","IdIndex":171},{"Rate":2.0,"Id":"10211031","IdIndex":173},{"Rate":2.0,"Id":"10211041","IdIndex":175},{"Rate":2.0,"Id":"10211021","IdIndex":170},{"Rate":2.0,"Id":"10211024","IdIndex":172},{"Rate":2.0,"Id":"10211034","IdIndex":174},{"Rate":2.0,"Id":"10211044","IdIndex":176},{"Rate":0.0,"Id":"10211018","IdIndex":168},{"Rate":0.0,"Id":"10211100-boss0","IdIndex":177}],"Area22":[{"Rate":2.0,"Id":"10221020","IdIndex":614},{"Rate":2.0,"Id":"10221023","IdIndex":617},{"Rate":2.0,"Id":"10221026","IdIndex":620},{"Rate":2.0,"Id":"10221059","IdIndex":649},{"Rate":2.0,"Id":"10221042","IdIndex":634},{"Rate":2.0,"Id":"10221059","IdIndex":649},{"Rate":2.0,"Id":"10221045","IdIndex":637},{"Rate":2.0,"Id":"10221024","IdIndex":618},{"Rate":0.0,"Id":"10221019","IdIndex":613}],"Area24":[{"Rate":1.0,"Id":"10231023","IdIndex":187},{"Rate":2.0,"Id":"10231026","IdIndex":188},{"Rate":1.0,"Id":"10231027","IdIndex":189},{"Rate":1.0,"Id":"10231034","IdIndex":191},{"Rate":1.0,"Id":"10231038","IdIndex":192},{"Rate":3.0,"Id":"10231043","IdIndex":193},{"Rate":3.0,"Id":"10231060","IdIndex":194},{"Rate":2.0,"Id":"10231029","IdIndex":190},{"Rate":0.0,"Id":"10231020","IdIndex":186},{"Rate":0.0,"Id":"10231100-boss0","IdIndex":195}],"Area25":[{"Rate":2.0,"Id":"10251024","IdIndex":726},{"Rate":2.0,"Id":"10251027","IdIndex":729},{"Rate":2.0,"Id":"10251030","IdIndex":732},{"Rate":2.0,"Id":"10251057","IdIndex":756},{"Rate":2.0,"Id":"10251028","IdIndex":730},{"Rate":2.0,"Id":"10251071","IdIndex":768},{"Rate":2.0,"Id":"10251081","IdIndex":777},{"Rate":2.0,"Id":"10251022","IdIndex":724},{"Rate":0.0,"Id":"10251021","IdIndex":723}],"Area27":[{"Rate":2.0,"Id":"10271023","IdIndex":224},{"Rate":2.0,"Id":"10271026","IdIndex":226},{"Rate":2.0,"Id":"10271029","IdIndex":228},{"Rate":2.0,"Id":"10271041","IdIndex":230},{"Rate":2.0,"Id":"10271031","IdIndex":229},{"Rate":2.0,"Id":"10271075","IdIndex":231},{"Rate":2.0,"Id":"10271025","IdIndex":225},{"Rate":2.0,"Id":"10271028","IdIndex":227},{"Rate":0.0,"Id":"10271022","IdIndex":223},{"Rate":0.0,"Id":"10271100-boss0","IdIndex":232}],"Area28":[{"Rate":2.0,"Id":"10281024","IdIndex":834},{"Rate":2.0,"Id":"10281027","IdIndex":837},{"Rate":2.0,"Id":"10281030","IdIndex":840},{"Rate":2.0,"Id":"10281033","IdIndex":843},{"Rate":2.0,"Id":"10281038","IdIndex":847},{"Rate":2.0,"Id":"10281118","IdIndex":916},{"Rate":2.0,"Id":"10281028","IdIndex":838},{"Rate":2.0,"Id":"10281025","IdIndex":835}],"Area29":[{"Rate":2.0,"Id":"10291028","IdIndex":921},{"Rate":2.0,"Id":"10291031","IdIndex":924},{"Rate":2.0,"Id":"10291034","IdIndex":927},{"Rate":2.0,"Id":"10291037","IdIndex":930},{"Rate":2.0,"Id":"10291141","IdIndex":1024},{"Rate":2.0,"Id":"10291038","IdIndex":931},{"Rate":2.0,"Id":"10291068","IdIndex":958},{"Rate":0.0,"Id":"10291024","IdIndex":917},{"Rate":0.0,"Id":"10291025","IdIndex":918},{"Rate":0.0,"Id":"10291026","IdIndex":919}],"Area30":[{"Rate":2.0,"Id":"10301029","IdIndex":1044},{"Rate":2.0,"Id":"10301032","IdIndex":1047},{"Rate":2.0,"Id":"10301035","IdIndex":1050},{"Rate":2.0,"Id":"10301038","IdIndex":1053},{"Rate":3.0,"Id":"10301136","IdIndex":1140},{"Rate":3.0,"Id":"10301089","IdIndex":1098},{"Rate":3.0,"Id":"10301082","IdIndex":1092},{"Rate":3.0,"Id":"10301116","IdIndex":1122},{"Rate":0.0,"Id":"10301025","IdIndex":1040},{"Rate":0.0,"Id":"10301026","IdIndex":1041}],"Area00":[{"Rate":0.0,"Id":"00001001","IdIndex":1},{"Rate":0.0,"Id":"00001002","IdIndex":2},{"Rate":0.0,"Id":"00001003","IdIndex":3}],"Area12":[{"Rate":3.0,"Id":"10121034","IdIndex":540},{"Rate":3.0,"Id":"10121037","IdIndex":543},{"Rate":3.0,"Id":"10121042","IdIndex":547},{"Rate":3.0,"Id":"10121044","IdIndex":549},{"Rate":3.0,"Id":"10121051","IdIndex":555}],"Area16":[{"Rate":2.0,"Id":"10161039","IdIndex":779},{"Rate":2.0,"Id":"10161042","IdIndex":782},{"Rate":2.0,"Id":"10161088","IdIndex":822},{"Rate":2.0,"Id":"10161045","IdIndex":785},{"Rate":2.0,"Id":"10161119","IdIndex":849},{"Rate":2.0,"Id":"10161040","IdIndex":780},{"Rate":2.0,"Id":"10161043","IdIndex":783},{"Rate":2.0,"Id":"10161046","IdIndex":786},{"Rate":2.0,"Id":"10161126","IdIndex":855},{"Rate":0.0,"Id":"10161047","IdIndex":787}],"Area17":[{"Rate":2.0,"Id":"10171042","IdIndex":918},{"Rate":2.0,"Id":"10171039","IdIndex":915},{"Rate":2.0,"Id":"10171045","IdIndex":921},{"Rate":2.0,"Id":"10171094","IdIndex":963},{"Rate":2.0,"Id":"10171085","IdIndex":956},{"Rate":2.0,"Id":"10171089","IdIndex":959},{"Rate":2.0,"Id":"10171096","IdIndex":965},{"Rate":2.0,"Id":"10171122","IdIndex":987},{"Rate":0.0,"Id":"10171046","IdIndex":922}],"Area23":[{"Rate":3.0,"Id":"10241041","IdIndex":463},{"Rate":3.0,"Id":"10241044","IdIndex":466},{"Rate":3.0,"Id":"10241083","IdIndex":499},{"Rate":3.0,"Id":"10241086","IdIndex":502},{"Rate":3.0,"Id":"10241072","IdIndex":490},{"Rate":0.0,"Id":"10241036","IdIndex":458}],"Area26":[{"Rate":2.0,"Id":"10261039","IdIndex":514},{"Rate":2.0,"Id":"10261042","IdIndex":517},{"Rate":2.0,"Id":"10261045","IdIndex":520},{"Rate":2.0,"Id":"10261049","IdIndex":523},{"Rate":2.0,"Id":"10261052","IdIndex":526},{"Rate":2.0,"Id":"10261056","IdIndex":529},{"Rate":2.0,"Id":"10261084","IdIndex":553},{"Rate":2.0,"Id":"10261087","IdIndex":556},{"Rate":2.0,"Id":"10261070","IdIndex":541},{"Rate":2.0,"Id":"10261059","IdIndex":532}],"Area31":[{"Rate":10.0,"Id":"10311032","IdIndex":1251},{"Rate":10.0,"Id":"10311033","IdIndex":1252},{"Rate":10.0,"Id":"10311031","IdIndex":1250},{"Rate":0.0,"Id":"10311037","IdIndex":1256},{"Rate":0.0,"Id":"10311040","IdIndex":1259},{"Rate":0.0,"Id":"10311043","IdIndex":1262},{"Rate":0.0,"Id":"10311046","IdIndex":1265}],"Area33":[{"Rate":2.0,"Id":"10331038","IdIndex":1406},{"Rate":2.0,"Id":"10331041","IdIndex":1409},{"Rate":2.0,"Id":"10331039","IdIndex":1407},{"Rate":2.0,"Id":"10331042","IdIndex":1410},{"Rate":1.0,"Id":"10331049","IdIndex":1416},{"Rate":1.0,"Id":"10331052","IdIndex":1419},{"Rate":2.0,"Id":"10331037","IdIndex":1405},{"Rate":2.0,"Id":"10331040","IdIndex":1408},{"Rate":0.0,"Id":"10331043","IdIndex":1411}],"Area34":[{"Rate":2.0,"Id":"10341050","IdIndex":299},{"Rate":2.0,"Id":"10341051","IdIndex":300},{"Rate":2.0,"Id":"10341052","IdIndex":301},{"Rate":2.0,"Id":"10331038","IdIndex":289},{"Rate":2.0,"Id":"10331041","IdIndex":292},{"Rate":2.0,"Id":"10331049","IdIndex":295},{"Rate":2.0,"Id":"10331039","IdIndex":290},{"Rate":2.0,"Id":"10331042","IdIndex":293}],"Area35":[{"Rate":2.0,"Id":"10331037","IdIndex":1405},{"Rate":2.0,"Id":"10331040","IdIndex":1408},{"Rate":2.0,"Id":"10341038","IdIndex":1450}],"Area36":[{"Rate":2.0,"Id":"10351051","IdIndex":1597},{"Rate":2.0,"Id":"10351052","IdIndex":1598},{"Rate":2.0,"Id":"10351053","IdIndex":1599},{"Rate":0.0,"Id":"10351039","IdIndex":1585},{"Rate":0.0,"Id":"10351042","IdIndex":1588},{"Rate":0.0,"Id":"10351045","IdIndex":1591},{"Rate":0.0,"Id":"10351048","IdIndex":1594},{"Rate":0.0,"Id":"10351054","IdIndex":1600}],"Area37":[{"Rate":2.0,"Id":"10241071","IdIndex":1124},{"Rate":2.0,"Id":"10241044","IdIndex":1100},{"Rate":2.0,"Id":"10241045","IdIndex":1101},{"Rate":2.0,"Id":"10241076","IdIndex":1128},{"Rate":2.0,"Id":"10241047","IdIndex":1103},{"Rate":2.0,"Id":"10241048","IdIndex":1104},{"Rate":2.0,"Id":"10241073","IdIndex":1125},{"Rate":2.0,"Id":"10241090","IdIndex":1140}],"Area38":[{"Rate":5.0,"Id":"10362553","IdIndex":324},{"Rate":5.0,"Id":"10362556","IdIndex":325},{"Rate":0.0,"Id":"10361042","IdIndex":311},{"Rate":0.0,"Id":"10361045","IdIndex":312},{"Rate":0.0,"Id":"10361048","IdIndex":313},{"Rate":0.0,"Id":"10361051","IdIndex":314},{"Rate":0.0,"Id":"10361054","IdIndex":315},{"Rate":0.0,"Id":"10361057","IdIndex":316},{"Rate":0.0,"Id":"10361060","IdIndex":317},{"Rate":0.0,"Id":"10361063","IdIndex":318},{"Rate":0.0,"Id":"10361066","IdIndex":319},{"Rate":0.0,"Id":"10361069","IdIndex":320},{"Rate":0.0,"Id":"10361072","IdIndex":321},{"Rate":0.0,"Id":"10361075","IdIndex":322},{"Rate":0.0,"Id":"10361078","IdIndex":323}]}