{"0":{"PrimaryKeyId":0,"Id":"000101","Type":"Task","IconId":"500020","Name":"多边形徽章","Desc":"一块拥有完美对称叶片的玉佩徽章.","SellPrice":-1,"BuyPrice":1,"CanDiscard":false,"Num":1,"MaxNum":1,"ChangeToId":"","Lv":1,"StringValue":""},"000101":{"PrimaryKeyId":0,"Id":"000101","Type":"Task","IconId":"500020","Name":"多边形徽章","Desc":"一块拥有完美对称叶片的玉佩徽章.","SellPrice":-1,"BuyPrice":1,"CanDiscard":false,"Num":1,"MaxNum":1,"ChangeToId":"","Lv":1,"StringValue":""},"000102":{"PrimaryKeyId":0,"Id":"000102","Type":"Book","IconId":"500019","Name":"村长珍藏的秘籍","Desc":"里面包着的像是一本册子.","SellPrice":-1,"BuyPrice":1,"CanDiscard":false,"Num":1,"MaxNum":1,"ChangeToId":"","Lv":1,"StringValue":"10001"},"000103":{"PrimaryKeyId":0,"Id":"000103","Type":"Normal","IconId":"500048","Name":"漕银","Desc":"装有漕银的盒子.","SellPrice":20,"BuyPrice":100000,"CanDiscard":true,"Num":1,"MaxNum":1,"ChangeToId":"","Lv":2,"StringValue":""},"000104":{"PrimaryKeyId":0,"Id":"000104","Type":"Normal","IconId":"500049","Name":"钱袋","Desc":"普通的钱袋,里面装了一点碎银子.","SellPrice":5,"BuyPrice":100000,"CanDiscard":true,"Num":1,"MaxNum":1,"ChangeToId":"","Lv":1,"StringValue":""},"000105":{"PrimaryKeyId":0,"Id":"000105","Type":"Normal","IconId":"500050","Name":"官银","Desc":"上了封条的箱子,里面装满了官银.","SellPrice":50,"BuyPrice":100000,"CanDiscard":true,"Num":1,"MaxNum":1,"ChangeToId":"","Lv":3,"StringValue":""},"000106":{"PrimaryKeyId":0,"Id":"000106","Type":"Normal","IconId":"500051","Name":"花石纲","Desc":"朝廷重金采购的石料,供当今圣上把玩.","SellPrice":100,"BuyPrice":100000,"CanDiscard":true,"Num":1,"MaxNum":1,"ChangeToId":"","Lv":4,"StringValue":""},"000107":{"PrimaryKeyId":0,"Id":"000107","Type":"Normal","IconId":"500052","Name":"玉璧","Desc":"古法制作的宝物,价值连城,各大城镇都有商人争相抢购.","SellPrice":300,"BuyPrice":100000,"CanDiscard":true,"Num":1,"MaxNum":1,"ChangeToId":"","Lv":5,"StringValue":""},"000108":{"PrimaryKeyId":0,"Id":"000108","Type":"Task","IconId":"500035","Name":"包袱","Desc":"一个行走江湖必备的包袱。","SellPrice":-1,"BuyPrice":1,"CanDiscard":false,"Num":1,"MaxNum":1,"ChangeToId":"","Lv":1,"StringValue":"10001"},"000109":{"PrimaryKeyId":0,"Id":"000109","Type":"Task","IconId":"500030","Name":"红花令","Desc":"通往丐帮总舵的必备信物。","SellPrice":-1,"BuyPrice":100000,"CanDiscard":false,"Num":1,"MaxNum":1,"ChangeToId":"","Lv":1,"StringValue":"30301"},"000110":{"PrimaryKeyId":0,"Id":"000110","Type":"Task","IconId":"500026","Name":"提刑司金令","Desc":"前往岳家军大营的令牌。","SellPrice":-1,"BuyPrice":100000,"CanDiscard":false,"Num":1,"MaxNum":1,"ChangeToId":"","Lv":1,"StringValue":"30101"},"000111":{"PrimaryKeyId":0,"Id":"000111","Type":"Task","IconId":"500049","Name":"锦囊","Desc":"瑛姑让你到达大理国境才能打开的锦囊。","SellPrice":-1,"BuyPrice":100000,"CanDiscard":false,"Num":1,"MaxNum":1,"ChangeToId":"","Lv":1,"StringValue":""},"000112":{"PrimaryKeyId":0,"Id":"000112","Type":"Task","IconId":"500032","Name":"赵志敬信物","Desc":"可以通行于终南山的信物。","SellPrice":-1,"BuyPrice":100000,"CanDiscard":false,"Num":1,"MaxNum":1,"ChangeToId":"","Lv":1,"StringValue":""},"000113":{"PrimaryKeyId":0,"Id":"000113","Type":"Task","IconId":"500031","Name":"觉远的佛珠","Desc":"觉远大师赠送的信物。","SellPrice":-1,"BuyPrice":100000,"CanDiscard":false,"Num":1,"MaxNum":1,"ChangeToId":"","Lv":1,"StringValue":""},"000114":{"PrimaryKeyId":0,"Id":"000114","Type":"Task","IconId":"500001","Name":"蛊毒解药","Desc":"魔教独门蛊毒的解药。","SellPrice":-1,"BuyPrice":100000,"CanDiscard":false,"Num":1,"MaxNum":1,"ChangeToId":"","Lv":1,"StringValue":""},"100001":{"PrimaryKeyId":0,"Id":"100001","Type":"Drug","IconId":"500043","Name":"金创散","Desc":"对外伤具有很好治疗效果的药物。(战斗中使用)","SellPrice":-1,"BuyPrice":5,"CanDiscard":true,"Num":1,"MaxNum":10,"ChangeToId":"","Lv":1,"StringValue":""},"100002":{"PrimaryKeyId":0,"Id":"100002","Type":"Drug","IconId":"500044","Name":"止血散","Desc":"可以快速止住流血的奇药。(战斗中使用)","SellPrice":-1,"BuyPrice":15,"CanDiscard":true,"Num":1,"MaxNum":10,"ChangeToId":"","Lv":2,"StringValue":""},"100003":{"PrimaryKeyId":0,"Id":"100003","Type":"Drug","IconId":"500045","Name":"白云散","Desc":"江湖中闻名的特效药物,比较常见。(战斗中使用)","SellPrice":-1,"BuyPrice":45,"CanDiscard":true,"Num":1,"MaxNum":10,"ChangeToId":"","Lv":3,"StringValue":""},"100004":{"PrimaryKeyId":0,"Id":"100004","Type":"Drug","IconId":"500046","Name":"天香云锦续","Desc":"罕见的特效疗伤药物,传闻是长白山高人所创。(战斗中使用)","SellPrice":-1,"BuyPrice":110,"CanDiscard":true,"Num":1,"MaxNum":6,"ChangeToId":"","Lv":4,"StringValue":""},"100005":{"PrimaryKeyId":0,"Id":"100005","Type":"Drug","IconId":"500047","Name":"黑玉断续膏","Desc":"金刚门的独门秘药,外表呈黑色,气息芬芳清凉。(战斗中使用)","SellPrice":-1,"BuyPrice":300,"CanDiscard":true,"Num":1,"MaxNum":6,"ChangeToId":"","Lv":5,"StringValue":""},"100006":{"PrimaryKeyId":0,"Id":"100006","Type":"Drug","IconId":"500053","Name":"无常丹","Desc":"主治内伤，每隔七天服一颗，廿一天後可伤愈。(战斗中使用)","SellPrice":-1,"BuyPrice":900,"CanDiscard":true,"Num":1,"MaxNum":6,"ChangeToId":"","Lv":6,"StringValue":""},"100007":{"PrimaryKeyId":0,"Id":"100007","Type":"Drug","IconId":"500054","Name":"田七鲨胆散","Desc":"江湖外伤神药，可快速恢复外伤。(战斗中使用)","SellPrice":-1,"BuyPrice":1900,"CanDiscard":true,"Num":1,"MaxNum":4,"ChangeToId":"","Lv":7,"StringValue":""},"100008":{"PrimaryKeyId":0,"Id":"100008","Type":"Drug","IconId":"500055","Name":"生生造化丹","Desc":"续命神丹,对碧蚕毒蛊,鹤顶红,孔雀胆三种刚毒有奇效。(战斗中使用)","SellPrice":-1,"BuyPrice":3100,"CanDiscard":true,"Num":1,"MaxNum":4,"ChangeToId":"","Lv":8,"StringValue":""},"100009":{"PrimaryKeyId":0,"Id":"100009","Type":"Drug","IconId":"500056","Name":"九转熊蛇丸","Desc":"疗伤圣药，呈黄色，散发一股极强烈的辛辣气只味，专治金创外伤，还魂续命，灵验无比。(战斗中使用)","SellPrice":-1,"BuyPrice":5800,"CanDiscard":true,"Num":1,"MaxNum":3,"ChangeToId":"","Lv":9,"StringValue":""},"100010":{"PrimaryKeyId":0,"Id":"100010","Type":"Drug","IconId":"500057","Name":"九转回春汤","Desc":"世间圣物,能疗绝症,解百毒,说得上有起死续命之功。(战斗中使用)","SellPrice":-1,"BuyPrice":8960,"CanDiscard":true,"Num":1,"MaxNum":2,"ChangeToId":"","Lv":10,"StringValue":""},"100101":{"PrimaryKeyId":0,"Id":"100101","Type":"Task","IconId":"500034","Name":"陆乘风亲笔信","Desc":"一封重要的信件，落款是“五湖废人”","SellPrice":-1,"BuyPrice":100000,"CanDiscard":false,"Num":1,"MaxNum":1,"ChangeToId":"","Lv":2,"StringValue":"10001"},"100102":{"PrimaryKeyId":0,"Id":"100102","Type":"Task","IconId":"500034","Name":"名帖","Desc":"加入任何一个江湖势力的新人都会得到的一张凭证","SellPrice":-1,"BuyPrice":1,"CanDiscard":false,"Num":1,"MaxNum":1,"ChangeToId":"","Lv":1,"StringValue":""},"100103":{"PrimaryKeyId":0,"Id":"100103","Type":"Book","IconId":"500036","Name":"丐帮初级秘籍","Desc":"里面装了一本丐帮的初级掌法秘籍。","SellPrice":-1,"BuyPrice":1,"CanDiscard":false,"Num":1,"MaxNum":1,"ChangeToId":"","Lv":1,"StringValue":"30101"},"100104":{"PrimaryKeyId":0,"Id":"100104","Type":"Book","IconId":"500036","Name":"少林初级秘籍","Desc":"里面装了一本少林寺初级棍法秘籍。","SellPrice":-1,"BuyPrice":1,"CanDiscard":false,"Num":1,"MaxNum":1,"ChangeToId":"","Lv":1,"StringValue":"30401"},"100105":{"PrimaryKeyId":0,"Id":"100105","Type":"Book","IconId":"500036","Name":"全真初级秘籍","Desc":"里面装了一本全真教初级掌法秘籍。","SellPrice":-1,"BuyPrice":1,"CanDiscard":false,"Num":1,"MaxNum":1,"ChangeToId":"","Lv":1,"StringValue":"30301"},"100106":{"PrimaryKeyId":0,"Id":"100106","Type":"Book","IconId":"500036","Name":"大理初级秘籍","Desc":"里面装了一本大理段氏的初级点穴手法秘籍。","SellPrice":-1,"BuyPrice":1,"CanDiscard":false,"Num":1,"MaxNum":1,"ChangeToId":"","Lv":1,"StringValue":"10015"},"100107":{"PrimaryKeyId":0,"Id":"100107","Type":"Book","IconId":"500036","Name":"岳家军初级秘籍","Desc":"里面装了一本岳家军初级枪法秘籍。","SellPrice":-1,"BuyPrice":1,"CanDiscard":false,"Num":1,"MaxNum":1,"ChangeToId":"","Lv":1,"StringValue":"30201"},"100108":{"PrimaryKeyId":0,"Id":"100108","Type":"Book","IconId":"500036","Name":"逍遥初级秘籍","Desc":"里面装了一本逍遥派的初级武功秘籍。","SellPrice":-1,"BuyPrice":1,"CanDiscard":false,"Num":1,"MaxNum":1,"ChangeToId":"","Lv":1,"StringValue":"30501"},"100109":{"PrimaryKeyId":0,"Id":"100109","Type":"Book","IconId":"500039","Name":"丐帮武功心法","Desc":"里面装了一本丐帮的招式心法。","SellPrice":-1,"BuyPrice":1,"CanDiscard":false,"Num":1,"MaxNum":1,"ChangeToId":"","Lv":2,"StringValue":"30102"},"100110":{"PrimaryKeyId":0,"Id":"100110","Type":"Book","IconId":"500039","Name":"少林武功心法","Desc":"里面装了一本少林寺武功心法。","SellPrice":-1,"BuyPrice":1,"CanDiscard":false,"Num":1,"MaxNum":1,"ChangeToId":"","Lv":2,"StringValue":"30402"},"100111":{"PrimaryKeyId":0,"Id":"100111","Type":"Book","IconId":"500039","Name":"全真武功心法","Desc":"里面装了一本全真教玄门正宗内功心法。","SellPrice":-1,"BuyPrice":1,"CanDiscard":false,"Num":1,"MaxNum":1,"ChangeToId":"","Lv":2,"StringValue":"16001"},"100112":{"PrimaryKeyId":0,"Id":"100112","Type":"Book","IconId":"500039","Name":"大理武功心法","Desc":"里面装了一本大理段氏不外传的内功心法。","SellPrice":-1,"BuyPrice":1,"CanDiscard":false,"Num":1,"MaxNum":1,"ChangeToId":"","Lv":2,"StringValue":"30601"},"100113":{"PrimaryKeyId":0,"Id":"100113","Type":"Book","IconId":"500039","Name":"岳家军密法","Desc":"里面装了一本岳家军的秘法。","SellPrice":-1,"BuyPrice":1,"CanDiscard":false,"Num":1,"MaxNum":1,"ChangeToId":"","Lv":2,"StringValue":"30202"},"100114":{"PrimaryKeyId":0,"Id":"100114","Type":"Book","IconId":"500039","Name":"逍遥派心法","Desc":"里面装了一本逍遥派的内功心法。","SellPrice":-1,"BuyPrice":1,"CanDiscard":false,"Num":1,"MaxNum":1,"ChangeToId":"","Lv":2,"StringValue":"30502"},"100115":{"PrimaryKeyId":0,"Id":"100115","Type":"Book","IconId":"500038","Name":"丐帮镇派秘籍","Desc":"一个装有丐帮的镇派秘籍的包袱。","SellPrice":-1,"BuyPrice":1,"CanDiscard":false,"Num":1,"MaxNum":1,"ChangeToId":"","Lv":3,"StringValue":"10021"},"100116":{"PrimaryKeyId":0,"Id":"100116","Type":"Book","IconId":"500038","Name":"少林镇派秘籍","Desc":"一个装有少林镇派绝学的包袱。","SellPrice":-1,"BuyPrice":1,"CanDiscard":false,"Num":1,"MaxNum":1,"ChangeToId":"","Lv":3,"StringValue":"30403"},"100117":{"PrimaryKeyId":0,"Id":"100117","Type":"Book","IconId":"500038","Name":"全真镇派秘籍","Desc":"一个装有全真教镇派绝学的包袱。","SellPrice":-1,"BuyPrice":1,"CanDiscard":false,"Num":1,"MaxNum":1,"ChangeToId":"","Lv":3,"StringValue":"30302"},"100118":{"PrimaryKeyId":0,"Id":"100118","Type":"Book","IconId":"500038","Name":"大理镇派秘籍","Desc":"一个装有大理镇派武学的包袱。","SellPrice":-1,"BuyPrice":1,"CanDiscard":false,"Num":1,"MaxNum":1,"ChangeToId":"","Lv":3,"StringValue":"30602"},"100119":{"PrimaryKeyId":0,"Id":"100119","Type":"Book","IconId":"500038","Name":"岳家军镇派秘籍","Desc":"一个装有岳家军镇派秘籍的包袱。","SellPrice":-1,"BuyPrice":1,"CanDiscard":false,"Num":1,"MaxNum":1,"ChangeToId":"","Lv":3,"StringValue":"30203"},"100120":{"PrimaryKeyId":0,"Id":"100120","Type":"Book","IconId":"500038","Name":"逍遥镇派秘籍","Desc":"一个装有逍遥派镇派绝学的包袱。","SellPrice":-1,"BuyPrice":1,"CanDiscard":false,"Num":1,"MaxNum":1,"ChangeToId":"","Lv":3,"StringValue":"30503"},"100121":{"PrimaryKeyId":0,"Id":"100121","Type":"Task","IconId":"500039","Name":"本门心法","Desc":"一个不太起眼的锦盒，是本门不传的宝物。","SellPrice":-1,"BuyPrice":1,"CanDiscard":true,"Num":1,"MaxNum":1,"ChangeToId":"","Lv":1,"StringValue":""},"100201":{"PrimaryKeyId":0,"Id":"100201","Type":"Food","IconId":"500006","Name":"一袋干粮","Desc":"粗粮做的，行走江湖必备的干粮。(在野外地图中可以补充体力)","SellPrice":1,"BuyPrice":1000,"CanDiscard":false,"Num":1,"MaxNum":5,"ChangeToId":"","Lv":1,"StringValue":""},"100202":{"PrimaryKeyId":0,"Id":"100202","Type":"Food","IconId":"500035","Name":"干粮包袱","Desc":"包袱里塞满了干粮以便闯荡江湖时充饥。(在野外地图中可以补充体力)","SellPrice":1,"BuyPrice":10,"CanDiscard":false,"Num":1,"MaxNum":10,"ChangeToId":"","Lv":1,"StringValue":""},"100203":{"PrimaryKeyId":0,"Id":"100203","Type":"Wheat","IconId":"500023","Name":"小麦辎重","Desc":"满满一框小麦。(可以带回城镇作为工坊的物资补给)","SellPrice":1,"BuyPrice":1000,"CanDiscard":false,"Num":1,"MaxNum":99,"ChangeToId":"","Lv":1,"StringValue":""},"100204":{"PrimaryKeyId":0,"Id":"100204","Type":"Wood","IconId":"500024","Name":"木材辎重","Desc":"一箱上等的木材。(可以带回城镇作为工坊的物资补给)","SellPrice":1,"BuyPrice":1000,"CanDiscard":false,"Num":1,"MaxNum":99,"ChangeToId":"","Lv":1,"StringValue":""},"100205":{"PrimaryKeyId":0,"Id":"100205","Type":"Stone","IconId":"500025","Name":"石料辎重","Desc":"一箱上等的石料。(可以带回城镇作为工坊的物资补给)","SellPrice":1,"BuyPrice":1000,"CanDiscard":false,"Num":1,"MaxNum":99,"ChangeToId":"","Lv":2,"StringValue":""},"100206":{"PrimaryKeyId":0,"Id":"100206","Type":"SilverOre","IconId":"500009","Name":"铁矿辎重","Desc":"一箱铁矿石。(可以带回城镇作为工坊的物资补给)","SellPrice":1,"BuyPrice":1000,"CanDiscard":false,"Num":1,"MaxNum":99,"ChangeToId":"","Lv":2,"StringValue":""},"100207":{"PrimaryKeyId":0,"Id":"100207","Type":"SilverOre","IconId":"500008","Name":"银矿辎重","Desc":"一箱银矿石。(可以带回城镇作为工坊的物资补给)","SellPrice":1,"BuyPrice":1000,"CanDiscard":false,"Num":1,"MaxNum":99,"ChangeToId":"","Lv":3,"StringValue":""},"100208":{"PrimaryKeyId":0,"Id":"100208","Type":"Steel","IconId":"500012","Name":"纯钢辎重","Desc":"一箱纯钢。(可以带回城镇作为工坊的物资补给)","SellPrice":1,"BuyPrice":1000,"CanDiscard":false,"Num":1,"MaxNum":99,"ChangeToId":"","Lv":3,"StringValue":""},"100209":{"PrimaryKeyId":0,"Id":"100209","Type":"Tungsten","IconId":"500011","Name":"钨矿辎重","Desc":"一箱钨矿石。(可以带回城镇作为工坊的物资补给)","SellPrice":1,"BuyPrice":1000,"CanDiscard":false,"Num":1,"MaxNum":99,"ChangeToId":"","Lv":4,"StringValue":""},"100210":{"PrimaryKeyId":0,"Id":"100210","Type":"Jade","IconId":"600009","Name":"玉石辎重","Desc":"一块上好的璞玉。(可以带回城镇作为工坊的物资补给)","SellPrice":1,"BuyPrice":1000,"CanDiscard":false,"Num":1,"MaxNum":99,"ChangeToId":"","Lv":4,"StringValue":""},"100211":{"PrimaryKeyId":0,"Id":"100211","Type":"RedSteel","IconId":"500013","Name":"赤铁辎重","Desc":"一箱珍贵的赤铁矿石。(可以带回城镇作为工坊的物资补给)","SellPrice":1,"BuyPrice":1000,"CanDiscard":false,"Num":1,"MaxNum":99,"ChangeToId":"","Lv":5,"StringValue":""},"100212":{"PrimaryKeyId":0,"Id":"100212","Type":"RefinedSteel","IconId":"500014","Name":"百炼钢辎重","Desc":"一箱百炼钢，十分珍贵。(可以带回城镇作为工坊的物资补给)","SellPrice":1,"BuyPrice":1000,"CanDiscard":false,"Num":1,"MaxNum":99,"ChangeToId":"","Lv":5,"StringValue":""},"100213":{"PrimaryKeyId":0,"Id":"100213","Type":"TungstenSteel","IconId":"500010","Name":"钨钢辎重","Desc":"一箱钨钢，属于朝廷的战略物资。(可以带回城镇作为工坊的物资补给)","SellPrice":1,"BuyPrice":1000,"CanDiscard":false,"Num":1,"MaxNum":99,"ChangeToId":"","Lv":6,"StringValue":""},"100214":{"PrimaryKeyId":0,"Id":"100214","Type":"Zingana","IconId":"500016","Name":"乌金木辎重","Desc":"一箱乌金木，造价十分高昂。(可以带回城镇作为工坊的物资补给)","SellPrice":1,"BuyPrice":1000,"CanDiscard":false,"Num":1,"MaxNum":99,"ChangeToId":"","Lv":7,"StringValue":""},"100215":{"PrimaryKeyId":0,"Id":"100215","Type":"DarksteelIngot","IconId":"500015","Name":"玄铁锭辎重","Desc":"一箱稀有的玄铁锭。(可以带回城镇作为工坊的物资补给)","SellPrice":1,"BuyPrice":1000,"CanDiscard":false,"Num":1,"MaxNum":99,"ChangeToId":"","Lv":8,"StringValue":""},"200001":{"PrimaryKeyId":0,"Id":"200001","Type":"Vulnerary","IconId":"500001","Name":"白日丹","Desc":"卖艺人常用的伤药。(能够治疗白伤)","SellPrice":1,"BuyPrice":10,"CanDiscard":true,"Num":1,"MaxNum":1,"ChangeToId":"","Lv":1,"StringValue":""},"200002":{"PrimaryKeyId":0,"Id":"200002","Type":"Vulnerary","IconId":"500002","Name":"全生丹","Desc":"对跌打损伤有奇效的伤药。(能够治疗黄伤)","SellPrice":2,"BuyPrice":50,"CanDiscard":true,"Num":1,"MaxNum":1,"ChangeToId":"","Lv":2,"StringValue":""},"200003":{"PrimaryKeyId":0,"Id":"200003","Type":"Vulnerary","IconId":"500003","Name":"小还丹","Desc":"其色碧绿，耗损真气后服此药，丹田热气升起，精力弥漫，可助功力的恢复。(能够治疗紫伤)","SellPrice":3,"BuyPrice":300,"CanDiscard":true,"Num":1,"MaxNum":1,"ChangeToId":"","Lv":3,"StringValue":""},"200004":{"PrimaryKeyId":0,"Id":"200004","Type":"Vulnerary","IconId":"500004","Name":"还阳丹","Desc":"江湖神物，无论多重的伤势都能药到病除。(能够治疗红伤)","SellPrice":4,"BuyPrice":1500,"CanDiscard":true,"Num":1,"MaxNum":1,"ChangeToId":"","Lv":4,"StringValue":""},"200005":{"PrimaryKeyId":0,"Id":"200005","Type":"Vulnerary","IconId":"500005","Name":"招魂丹","Desc":"此丹药不仅能起死回生，而且有疗治一切内、外伤及增加功力之效。(能够救治垂死之人)","SellPrice":5,"BuyPrice":5000,"CanDiscard":true,"Num":1,"MaxNum":1,"ChangeToId":"","Lv":5,"StringValue":""},"300101":{"PrimaryKeyId":0,"Id":"300101","Type":"SecretIncreaseMaxHP","IconId":"800101","Name":"涌泉","Desc":"","SellPrice":-1,"BuyPrice":100000,"CanDiscard":true,"Num":1,"MaxNum":1,"ChangeToId":"","Lv":1,"StringValue":""},"300102":{"PrimaryKeyId":0,"Id":"300102","Type":"SecreIncreaseMaxHPRate","IconId":"800102","Name":"飞仙","Desc":"","SellPrice":-1,"BuyPrice":100000,"CanDiscard":true,"Num":1,"MaxNum":1,"ChangeToId":"","Lv":1,"StringValue":""},"300103":{"PrimaryKeyId":0,"Id":"300103","Type":"SecreIncreasePhysicsAttack","IconId":"800103","Name":"破甲","Desc":"","SellPrice":-1,"BuyPrice":100000,"CanDiscard":true,"Num":1,"MaxNum":1,"ChangeToId":"","Lv":1,"StringValue":""},"300104":{"PrimaryKeyId":0,"Id":"300104","Type":"SecreIncreasePhysicsAttackRate","IconId":"800104","Name":"开山","Desc":"","SellPrice":-1,"BuyPrice":100000,"CanDiscard":true,"Num":1,"MaxNum":1,"ChangeToId":"","Lv":1,"StringValue":""},"300105":{"PrimaryKeyId":0,"Id":"300105","Type":"SecreIncreasePhysicsDefense","IconId":"800105","Name":"坚毅","Desc":"","SellPrice":-1,"BuyPrice":100000,"CanDiscard":true,"Num":1,"MaxNum":1,"ChangeToId":"","Lv":1,"StringValue":""},"300106":{"PrimaryKeyId":0,"Id":"300106","Type":"SecreIncreasePhysicsDefenseRate","IconId":"800106","Name":"刚强","Desc":"","SellPrice":-1,"BuyPrice":100000,"CanDiscard":true,"Num":1,"MaxNum":1,"ChangeToId":"","Lv":1,"StringValue":""},"300107":{"PrimaryKeyId":0,"Id":"300107","Type":"SecreIncreaseMagicAttack","IconId":"800107","Name":"暗流","Desc":"","SellPrice":-1,"BuyPrice":100000,"CanDiscard":true,"Num":1,"MaxNum":1,"ChangeToId":"","Lv":1,"StringValue":""},"300108":{"PrimaryKeyId":0,"Id":"300108","Type":"SecreIncreaseMagicAttackRate","IconId":"800108","Name":"怒涛","Desc":"","SellPrice":-1,"BuyPrice":100000,"CanDiscard":true,"Num":1,"MaxNum":1,"ChangeToId":"","Lv":1,"StringValue":""},"300109":{"PrimaryKeyId":0,"Id":"300109","Type":"SecreIncreaseMagicDefense","IconId":"800109","Name":"磐石","Desc":"","SellPrice":-1,"BuyPrice":100000,"CanDiscard":true,"Num":1,"MaxNum":1,"ChangeToId":"","Lv":1,"StringValue":""},"300110":{"PrimaryKeyId":0,"Id":"300110","Type":"SecreIncreaseMagicDefenseRate","IconId":"800110","Name":"涅槃","Desc":"","SellPrice":-1,"BuyPrice":100000,"CanDiscard":true,"Num":1,"MaxNum":1,"ChangeToId":"","Lv":1,"StringValue":""},"300111":{"PrimaryKeyId":0,"Id":"300111","Type":"SecreIncreaseFixedDamage","IconId":"800111","Name":"追命","Desc":"","SellPrice":-1,"BuyPrice":100000,"CanDiscard":true,"Num":1,"MaxNum":1,"ChangeToId":"","Lv":1,"StringValue":""},"300112":{"PrimaryKeyId":0,"Id":"300112","Type":"SecreIncreaseDamageRate","IconId":"800112","Name":"骁勇","Desc":"","SellPrice":-1,"BuyPrice":100000,"CanDiscard":true,"Num":1,"MaxNum":1,"ChangeToId":"","Lv":1,"StringValue":""},"300113":{"PrimaryKeyId":0,"Id":"300113","Type":"SecreIncreaseHurtCutRate","IconId":"800113","Name":"布阵","Desc":"","SellPrice":-1,"BuyPrice":100000,"CanDiscard":true,"Num":1,"MaxNum":1,"ChangeToId":"","Lv":1,"StringValue":""},"300114":{"PrimaryKeyId":0,"Id":"300114","Type":"SecreIncreaseDodge","IconId":"800114","Name":"轻灵","Desc":"","SellPrice":-1,"BuyPrice":100000,"CanDiscard":true,"Num":1,"MaxNum":1,"ChangeToId":"","Lv":1,"StringValue":""},"300115":{"PrimaryKeyId":0,"Id":"300115","Type":"SecreDrugResistance","IconId":"800115","Name":"驭毒","Desc":"","SellPrice":-1,"BuyPrice":100000,"CanDiscard":true,"Num":1,"MaxNum":1,"ChangeToId":"","Lv":1,"StringValue":""},"300116":{"PrimaryKeyId":0,"Id":"300116","Type":"SecreDisarmResistance","IconId":"800116","Name":"站桩","Desc":"","SellPrice":-1,"BuyPrice":100000,"CanDiscard":true,"Num":1,"MaxNum":1,"ChangeToId":"","Lv":1,"StringValue":""},"300117":{"PrimaryKeyId":0,"Id":"300117","Type":"SecreVertigoResistance","IconId":"800117","Name":"清醒","Desc":"","SellPrice":-1,"BuyPrice":100000,"CanDiscard":true,"Num":1,"MaxNum":1,"ChangeToId":"","Lv":1,"StringValue":""},"300118":{"PrimaryKeyId":0,"Id":"300118","Type":"SecreCanNotMoveResistance","IconId":"800118","Name":"腾挪","Desc":"","SellPrice":-1,"BuyPrice":100000,"CanDiscard":true,"Num":1,"MaxNum":1,"ChangeToId":"","Lv":1,"StringValue":""},"300119":{"PrimaryKeyId":0,"Id":"300119","Type":"SecreSlowResistance","IconId":"800119","Name":"敏锐","Desc":"","SellPrice":-1,"BuyPrice":100000,"CanDiscard":true,"Num":1,"MaxNum":1,"ChangeToId":"","Lv":1,"StringValue":""},"300120":{"PrimaryKeyId":0,"Id":"300120","Type":"SecreChaosResistance","IconId":"800120","Name":"沉稳","Desc":"","SellPrice":-1,"BuyPrice":100000,"CanDiscard":true,"Num":1,"MaxNum":1,"ChangeToId":"","Lv":1,"StringValue":""},"300122":{"PrimaryKeyId":0,"Id":"300122","Type":"SecreCutCD","IconId":"800122","Name":"行云流水","Desc":"","SellPrice":-1,"BuyPrice":100000,"CanDiscard":true,"Num":1,"MaxNum":1,"ChangeToId":"","Lv":1,"StringValue":""},"300123":{"PrimaryKeyId":0,"Id":"300123","Type":"SecreImmortal","IconId":"800123","Name":"不死金刚","Desc":"","SellPrice":-1,"BuyPrice":100000,"CanDiscard":true,"Num":1,"MaxNum":1,"ChangeToId":"","Lv":1,"StringValue":""},"300124":{"PrimaryKeyId":0,"Id":"300124","Type":"SecreKilled","IconId":"800124","Name":"一击必杀","Desc":"","SellPrice":-1,"BuyPrice":100000,"CanDiscard":true,"Num":1,"MaxNum":1,"ChangeToId":"","Lv":1,"StringValue":""},"300125":{"PrimaryKeyId":0,"Id":"300125","Type":"SecreMakeAFortune","IconId":"800125","Name":"盆满钵满","Desc":"","SellPrice":-1,"BuyPrice":100000,"CanDiscard":true,"Num":1,"MaxNum":1,"ChangeToId":"","Lv":1,"StringValue":""},"301001":{"PrimaryKeyId":0,"Id":"301001","Type":"Normal","IconId":"500059","Name":"秘籍修为","Desc":"","SellPrice":-1,"BuyPrice":100000,"CanDiscard":true,"Num":1,"MaxNum":999,"ChangeToId":"","Lv":1,"StringValue":"30401"},"test0":{"PrimaryKeyId":0,"Id":"test0","Type":"Weapon","IconId":"500038","Name":"测试闪金兵器","Desc":"","SellPrice":0,"BuyPrice":1,"CanDiscard":true,"Num":1,"MaxNum":1,"ChangeToId":"","Lv":1,"StringValue":"100106"}}